odoo10_addon_l10n_it_corrispettivi-10.0.1.2.3-py2.7-nspkg.pth
odoo/addons/l10n_it_corrispettivi/README.rst
odoo/addons/l10n_it_corrispettivi/__init__.py
odoo/addons/l10n_it_corrispettivi/__manifest__.py
odoo/addons/l10n_it_corrispettivi/i18n/am.po
odoo/addons/l10n_it_corrispettivi/i18n/ar.po
odoo/addons/l10n_it_corrispettivi/i18n/bg.po
odoo/addons/l10n_it_corrispettivi/i18n/bs.po
odoo/addons/l10n_it_corrispettivi/i18n/ca.po
odoo/addons/l10n_it_corrispettivi/i18n/cs.po
odoo/addons/l10n_it_corrispettivi/i18n/da.po
odoo/addons/l10n_it_corrispettivi/i18n/de.po
odoo/addons/l10n_it_corrispettivi/i18n/el_GR.po
odoo/addons/l10n_it_corrispettivi/i18n/en_GB.po
odoo/addons/l10n_it_corrispettivi/i18n/es.po
odoo/addons/l10n_it_corrispettivi/i18n/es_AR.po
odoo/addons/l10n_it_corrispettivi/i18n/es_CR.po
odoo/addons/l10n_it_corrispettivi/i18n/es_EC.po
odoo/addons/l10n_it_corrispettivi/i18n/es_MX.po
odoo/addons/l10n_it_corrispettivi/i18n/es_VE.po
odoo/addons/l10n_it_corrispettivi/i18n/et.po
odoo/addons/l10n_it_corrispettivi/i18n/fi.po
odoo/addons/l10n_it_corrispettivi/i18n/fr.po
odoo/addons/l10n_it_corrispettivi/i18n/fr_CA.po
odoo/addons/l10n_it_corrispettivi/i18n/fr_CH.po
odoo/addons/l10n_it_corrispettivi/i18n/gl.po
odoo/addons/l10n_it_corrispettivi/i18n/hr.po
odoo/addons/l10n_it_corrispettivi/i18n/hr_HR.po
odoo/addons/l10n_it_corrispettivi/i18n/hu.po
odoo/addons/l10n_it_corrispettivi/i18n/id.po
odoo/addons/l10n_it_corrispettivi/i18n/it.po
odoo/addons/l10n_it_corrispettivi/i18n/ja.po
odoo/addons/l10n_it_corrispettivi/i18n/l10n_it_corrispettivi.pot
odoo/addons/l10n_it_corrispettivi/i18n/lt.po
odoo/addons/l10n_it_corrispettivi/i18n/lv.po
odoo/addons/l10n_it_corrispettivi/i18n/mk.po
odoo/addons/l10n_it_corrispettivi/i18n/mn.po
odoo/addons/l10n_it_corrispettivi/i18n/nb.po
odoo/addons/l10n_it_corrispettivi/i18n/nb_NO.po
odoo/addons/l10n_it_corrispettivi/i18n/nl.po
odoo/addons/l10n_it_corrispettivi/i18n/nl_BE.po
odoo10_addon_l10n_it_corrispettivi-10.0.1.2.3.dist-info/METADATA
odoo10_addon_l10n_it_corrispettivi-10.0.1.2.3.dist-info/RECORD
odoo10_addon_l10n_it_corrispettivi-10.0.1.2.3.dist-info/WHEEL
odoo10_addon_l10n_it_corrispettivi-10.0.1.2.3.dist-info/namespace_packages.txt
odoo10_addon_l10n_it_corrispettivi-10.0.1.2.3.dist-info/top_level.txt
