Metadata-Version: 2.1
Name: odoo10-addon-l10n-it-corrispettivi
Version: 10.0.1.2.3
Summary: Italian Localization - Corrispettivi
Home-page: https://github.com/OCA/l10n-italy/tree/10.0/l10n_it_corrispettivi
Author: Odoo Italian Community, Agile Business Group, Odoo Community Association (OCA)
Author-email: support@odoo-community.org
License: LGPL-3
Platform: UNKNOWN
Classifier: Programming Language :: Python
Classifier: Framework :: Odoo
Classifier: License :: OSI Approved :: GNU Lesser General Public License v3 (LGPLv3)
Requires-Python: ~=2.7
Requires-Dist: odoo (<10.1dev,>=10.0)
